LICENSE
MANIFEST.in
README.rst
helga_oral_history.py
setup.py
helga_oral_history.egg-info/PKG-INFO
helga_oral_history.egg-info/SOURCES.txt
helga_oral_history.egg-info/dependency_links.txt
helga_oral_history.egg-info/entry_points.txt
helga_oral_history.egg-info/requires.txt
helga_oral_history.egg-info/top_level.txt
helga_oral_history.egg-info/zip-safe