Metadata-Version: 1.1
Name: helga-oral-history
Version: 0.2.0
Summary: A (mosty) good recounting of what helga heas
Home-page: UNKNOWN
Author: Justin Caratzas
Author-email: bigjust@lambdaphil.es
License: LICENSE
Keywords: irc bot oral-history
Platform: UNKNOWN
Classifier: Development Status :: 3 - Alpha
Classifier: License :: OSI Approved :: GNU General Public License v3 (GPLv3)
Classifier: Operating System :: OS Independent
Classifier: Programming Language :: Python
Classifier: Topic :: Software Development :: Libraries :: Python Modules
